codemeta.json
tvbwidgets/__init__.py
tvbwidgets/api.py
tvbwidgets/readers.py
tvbwidgets/core/__init__.py
tvbwidgets/core/auth.py
tvbwidgets/core/exceptions.py
tvbwidgets/core/ini_parser.py
tvbwidgets/core/bucket/__init__.py
tvbwidgets/core/bucket/bucket_api.py
tvbwidgets/core/bucket/buckets.py
tvbwidgets/core/hpc/__init__.py
tvbwidgets/core/hpc/config.py
tvbwidgets/core/hpc/launcher.py
tvbwidgets/core/logger/__init__.py
tvbwidgets/core/logger/builder.py
tvbwidgets/core/logger/logging.conf
tvbwidgets/core/pse/__init__.py
tvbwidgets/core/pse/parameters.py
tvbwidgets/core/pse/pse_data.py
tvbwidgets/core/pse/storage.py
tvbwidgets/core/pse/toml_storage.py
tvbwidgets/core/simulator/__init__.py
tvbwidgets/core/simulator/model_exporters.py
tvbwidgets/core/simulator/tvb_integrators.py
tvbwidgets/tests/__init__.py
tvbwidgets/tests/constants.py
tvbwidgets/tests/test_base.py
tvbwidgets/tests/test_bucket_widget.py
tvbwidgets/tests/test_connectivity_matrix_editor_widget.py
tvbwidgets/tests/test_drive_widget.py
tvbwidgets/tests/test_exporters.py
tvbwidgets/tests/test_head_widget.py
tvbwidgets/tests/test_phase_plane_export.py
tvbwidgets/tests/test_pse_stage_in.py
tvbwidgets/tests/test_readers.py
tvbwidgets/tests/test_spacetime_widget.py
tvbwidgets/tests/test_tvb_integrators.py
tvbwidgets/tests/data/test_file.edf
tvbwidgets/tests/ts/__init__.py
tvbwidgets/tests/ts/test_data_wrappers.py
tvbwidgets/tests/ts/test_mne_widget.py
tvbwidgets/tests/ts/test_plotly_widget.py
tvbwidgets/tests/ts/ts_generator.py
tvbwidgets/ui/__init__.py
tvbwidgets/ui/base_widget.py
tvbwidgets/ui/bucket_widget.py
tvbwidgets/ui/connectivity_matrix_editor_widget.py
tvbwidgets/ui/dicom_widget.py
tvbwidgets/ui/drive_widget.py
tvbwidgets/ui/head_widget.py
tvbwidgets/ui/phase_plane_widget.py
tvbwidgets/ui/pse_launcher_widget.py
tvbwidgets/ui/pse_widget.py
tvbwidgets/ui/spacetime_widget.py
tvbwidgets/ui/storage_widget.py
tvbwidgets/ui/widget_with_browser.py
tvbwidgets/ui/connectivity_ipy/__init__.py
tvb_widgets-2.3.2.dist-info/METADATA
tvb_widgets-2.3.2.dist-info/WHEEL
tvb_widgets-2.3.2.dist-info/licenses/LICENSE
tvb_widgets-2.3.2.dist-info/RECORD
