Metadata-Version: 2.4
Name: tvb-widgets
Version: 2.3.2
Summary: TheVirtualBrain - Widgets is a package with somehow generic GUI components, but developed for EBRAINS Showcases in particular.
Project-URL: Homepage, https://github.com/the-virtual-brain/tvb-widgets
Author-email: "TVB Widgets Team (Juelich SDL Neuroscience, INS - Marseille, Codemart)" <tvb.admin@thevirtualbrain.org>
License: "TheVirtualBrain - Widgets" is a package with GUI components for EBRAINS
License-File: LICENSE
Keywords: components,ebrains,jupyterlab,tvb,widgets
Classifier: License :: OSI Approved :: GNU General Public License v3 or later (GPLv3+)
Classifier: Programming Language :: Python :: 3
Classifier: Programming Language :: Python :: 3.8
Classifier: Programming Language :: Python :: 3.9
Classifier: Programming Language :: Python :: 3.10
Classifier: Programming Language :: Python :: 3.11
Requires-Python: >=3.8
Requires-Dist: bokeh
Requires-Dist: colorcet
Requires-Dist: ebrains-drive
Requires-Dist: ipycanvas
Requires-Dist: ipympl>0.8.5
Requires-Dist: ipyreact>=0.4.1
Requires-Dist: ipython<=8.12
Requires-Dist: ipywidgets==8.0.7
Requires-Dist: joblib
Requires-Dist: k3d<2.17.0
Requires-Dist: mne>=1.0
Requires-Dist: numpy
Requires-Dist: plotly-resampler
Requires-Dist: plotly==5.14.0
Requires-Dist: pyunicore>=1.0.0
Requires-Dist: requests
Requires-Dist: toml
Requires-Dist: traitlets>=5.7.1
Requires-Dist: tvb-framework
Requires-Dist: tvb-library
Provides-Extra: examples
Requires-Dist: tvb-data; extra == 'examples'
Provides-Extra: tests
Requires-Dist: pytest; extra == 'tests'
Requires-Dist: pytest-mock; extra == 'tests'
